{
  "version": 1,
  "updated": "2026-06-12T01:36:56Z",
  "rates": [
    {
      "id": "binance_th_usdt",
      "name": "Binance TH",
      "ok": true,
      "thbPerUsdt": 32.76,
      "fetchedAt": "2026-06-12T01:36:56Z"
    },
    {
      "id": "bitkub_usdt",
      "name": "Bitkub",
      "ok": true,
      "thbPerUsdt": 32.76,
      "fetchedAt": "2026-06-12T01:36:56Z"
    },
    {
      "id": "bitazza_usdt",
      "name": "Bitazza",
      "ok": true,
      "thbPerUsdt": 32.75,
      "fetchedAt": "2026-06-12T01:36:56Z"
    }
  ]
}
